{
  "subtitle": "Home - Our Trainers",
  "title": "Our Trainers",
  "filters": [
    {
      "name": "category",
      "options": ["kickboxing", "kinboxing", "strength", "yoga"]
    },
    {
      "name": "area",
      "options": ["berlin", "amsterdam", "hamburg", "budapest"]
    },
    {
      "name": "rating",
      "options": [1, 2, 3, 4, 5]
    },
    {
      "name": "experience",
      "options": ["1 year +", "2 year +", "3 year +"]
    }
  ],
  "results": [
    {
      "category": "Popular Trainers",
      "list": [
        {
          "name": "Victoria",
          "id": "123",
          "image": "",
          "video": "",
          "rating": 4,
          "ratedBy": 45,
          "topReviews": [
            {
              "rating": 3,
              "name": "Johny Lobson",
              "thumbnail": "",
              "title": "Very good",
              "comment": "I used her services"
            },
            {
              "rating": 3,
              "name": "Johny Lobson",
              "thumbnail": "",
              "title": "Very good",
              "comment": "I used her services"
            }
          ],
          "description":
            "$ years of experience in kickboxing, Victoria is best suited to help you"
        },
        {
          "name": "Victoria",
          "id": "123",
          "video": "",
          "image": "",
          "rating": 4,
          "ratedBy": 45,
          "topReviews": [
            {
              "rating": 3,
              "name": "Johny Lobson",
              "thumbnail": "",
              "title": "Very good",
              "comment": "I used her services"
            },
            {
              "rating": 3,
              "name": "Johny Lobson",
              "thumbnail": "",
              "title": "Very good",
              "comment": "I used her services"
            }
          ],
          "description":
            "$ years of experience in kickboxing, Victoria is best suited to help you"
        },
        {
          "name": "Victoria",
          "id": "123",
          "video": "",
          "image": "",
          "rating": 4,
          "ratedBy": 45,
          "topReviews": [
            {
              "rating": 3,
              "name": "Johny Lobson",
              "thumbnail": "",
              "title": "Very good",
              "comment": "I used her services"
            },
            {
              "rating": 3,
              "name": "Johny Lobson",
              "thumbnail": "",
              "title": "Very good",
              "comment": "I used her services"
            }
          ],
          "description":
            "$ years of experience in kickboxing, Victoria is best suited to help you"
        },
        {
          "name": "Victoria",
          "id": "123",
          "video": "",
          "image": "",
          "rating": 4,
          "ratedBy": 45,
          "topReviews": [
            {
              "rating": 3,
              "name": "Johny Lobson",
              "thumbnail": "",
              "title": "Very good",
              "comment": "I used her services"
            },
            {
              "rating": 3,
              "name": "Johny Lobson",
              "thumbnail": "",
              "title": "Very good",
              "comment": "I used her services"
            }
          ],
          "description":
            "$ years of experience in kickboxing, Victoria is best suited to help you"
        },
        {
          "name": "Victoria",
          "id": "123",
          "video": "",
          "image": "",
          "rating": 4,
          "ratedBy": 45,
          "topReviews": [
            {
              "rating": 3,
              "name": "Johny Lobson",
              "thumbnail": "",
              "title": "Very good",
              "comment": "I used her services"
            },
            {
              "rating": 3,
              "name": "Johny Lobson",
              "thumbnail": "",
              "title": "Very good",
              "comment": "I used her services"
            }
          ],
          "description":
            "$ years of experience in kickboxing, Victoria is best suited to help you"
        }
      ]
    },
    {
      "category": "Kickboxing",
      "list": [
        {
          "name": "Victoria",
          "id": "123",
          "video": "",
          "image": "",
          "rating": 4,
          "ratedBy": 45,
          "topReviews": [
            {
              "rating": 3,
              "name": "Johny Lobson",
              "thumbnail": "",
              "title": "Very good",
              "comment": "I used her services"
            },
            {
              "rating": 3,
              "name": "Johny Lobson",
              "thumbnail": "",
              "title": "Very good",
              "comment": "I used her services"
            }
          ],
          "description":
            "$ years of experience in kickboxing, Victoria is best suited to help you"
        },
        {
          "name": "Victoria",
          "id": "123",
          "video": "",
          "image": "",
          "rating": 4,
          "ratedBy": 45,
          "topReviews": [
            {
              "rating": 3,
              "name": "Johny Lobson",
              "thumbnail": "",
              "title": "Very good",
              "comment": "I used her services"
            },
            {
              "rating": 3,
              "name": "Johny Lobson",
              "thumbnail": "",
              "title": "Very good",
              "comment": "I used her services"
            }
          ],
          "description":
            "$ years of experience in kickboxing, Victoria is best suited to help you"
        },
        {
          "name": "Victoria",
          "id": "123",
          "video": "",
          "image": "",
          "rating": 4,
          "ratedBy": 45,
          "topReviews": [
            {
              "rating": 3,
              "name": "Johny Lobson",
              "thumbnail": "",
              "title": "Very good",
              "comment": "I used her services"
            },
            {
              "rating": 3,
              "name": "Johny Lobson",
              "thumbnail": "",
              "title": "Very good",
              "comment": "I used her services"
            }
          ],
          "description":
            "$ years of experience in kickboxing, Victoria is best suited to help you"
        },
        {
          "name": "Victoria",
          "id": "123",
          "video": "",
          "image": "",
          "rating": 4,
          "ratedBy": 45,
          "topReviews": [
            {
              "rating": 3,
              "name": "Johny Lobson",
              "thumbnail": "",
              "title": "Very good",
              "comment": "I used her services"
            },
            {
              "rating": 3,
              "name": "Johny Lobson",
              "thumbnail": "",
              "title": "Very good",
              "comment": "I used her services"
            }
          ],
          "description":
            "$ years of experience in kickboxing, Victoria is best suited to help you"
        },
        {
          "name": "Victoria",
          "id": "123",
          "video": "",
          "image": "",
          "rating": 4,
          "ratedBy": 45,
          "topReviews": [
            {
              "rating": 3,
              "name": "Johny Lobson",
              "thumbnail": "",
              "title": "Very good",
              "comment": "I used her services"
            },
            {
              "rating": 3,
              "name": "Johny Lobson",
              "thumbnail": "",
              "title": "Very good",
              "comment": "I used her services"
            }
          ],
          "description":
            "$ years of experience in kickboxing, Victoria is best suited to help you"
        },
        {
          "name": "Victoria",
          "id": "123",
          "image": "",
          "video": "",
          "rating": 4,
          "ratedBy": 45,
          "topReviews": [
            {
              "rating": 3,
              "name": "Johny Lobson",
              "thumbnail": "",
              "title": "Very good",
              "comment": "I used her services"
            },
            {
              "rating": 3,
              "name": "Johny Lobson",
              "thumbnail": "",
              "title": "Very good",
              "comment": "I used her services"
            }
          ],
          "description":
            "$ years of experience in kickboxing, Victoria is best suited to help you"
        }
      ]
    },
    {
      "category": "Yoga",
      "list": [
        {
          "name": "Victoria",
          "id": "123",
          "video": "",
          "image": "",
          "rating": 4,
          "ratedBy": 45,
          "topReviews": [
            {
              "rating": 3,
              "name": "Johny Lobson",
              "thumbnail": "",
              "title": "Very good",
              "comment": "I used her services"
            },
            {
              "rating": 3,
              "name": "Johny Lobson",
              "thumbnail": "",
              "title": "Very good",
              "comment": "I used her services"
            }
          ],
          "description":
            "$ years of experience in kickboxing, Victoria is best suited to help you"
        },
        {
          "name": "Victoria",
          "id": "123",
          "image": "",
          "video": "",
          "rating": 4,
          "ratedBy": 45,
          "topReviews": [
            {
              "rating": 3,
              "name": "Johny Lobson",
              "thumbnail": "",
              "title": "Very good",
              "comment": "I used her services"
            },
            {
              "rating": 3,
              "name": "Johny Lobson",
              "thumbnail": "",
              "title": "Very good",
              "comment": "I used her services"
            }
          ],
          "description":
            "$ years of experience in kickboxing, Victoria is best suited to help you"
        },
        {
          "name": "Victoria",
          "id": "123",
          "image": "",
          "video": "",
          "rating": 4,
          "ratedBy": 45,
          "topReviews": [
            {
              "rating": 3,
              "name": "Johny Lobson",
              "thumbnail": "",
              "title": "Very good",
              "comment": "I used her services"
            },
            {
              "rating": 3,
              "name": "Johny Lobson",
              "thumbnail": "",
              "title": "Very good",
              "comment": "I used her services"
            }
          ],
          "description":
            "$ years of experience in kickboxing, Victoria is best suited to help you"
        },
        {
          "name": "Victoria",
          "id": "123",
          "video": "",
          "image": "",
          "rating": 4,
          "ratedBy": 45,
          "topReviews": [
            {
              "rating": 3,
              "name": "Johny Lobson",
              "thumbnail": "",
              "title": "Very good",
              "comment": "I used her services"
            },
            {
              "rating": 3,
              "name": "Johny Lobson",
              "thumbnail": "",
              "title": "Very good",
              "comment": "I used her services"
            }
          ],
          "description":
            "$ years of experience in kickboxing, Victoria is best suited to help you"
        },
        {
          "name": "Victoria",
          "id": "123",
          "video": "",
          "image": "",
          "rating": 4,
          "ratedBy": 45,
          "topReviews": [
            {
              "rating": 3,
              "name": "Johny Lobson",
              "thumbnail": "",
              "title": "Very good",
              "comment": "I used her services"
            },
            {
              "rating": 3,
              "name": "Johny Lobson",
              "thumbnail": "",
              "title": "Very good",
              "comment": "I used her services"
            }
          ],
          "description":
            "$ years of experience in kickboxing, Victoria is best suited to help you"
        },
        {
          "name": "Victoria",
          "id": "123",
          "video": "",
          "image": "",
          "rating": 4,
          "ratedBy": 45,
          "topReviews": [
            {
              "rating": 3,
              "name": "Johny Lobson",
              "thumbnail": "",
              "title": "Very good",
              "comment": "I used her services"
            },
            {
              "rating": 3,
              "name": "Johny Lobson",
              "thumbnail": "",
              "title": "Very good",
              "comment": "I used her services"
            }
          ],
          "description":
            "$ years of experience in kickboxing, Victoria is best suited to help you"
        }
      ]
    },
    {
      "category": "Strength",
      "list": [
        {
          "name": "Victoria",
          "id": "123",
          "video": "",
          "image": "",
          "rating": 4,
          "ratedBy": 45,
          "topReviews": [
            {
              "rating": 3,
              "name": "Johny Lobson",
              "thumbnail": "",
              "title": "Very good",
              "comment": "I used her services"
            },
            {
              "rating": 3,
              "name": "Johny Lobson",
              "thumbnail": "",
              "title": "Very good",
              "comment": "I used her services"
            }
          ],
          "description":
            "$ years of experience in kickboxing, Victoria is best suited to help you"
        },
        {
          "name": "Victoria",
          "id": "123",
          "video": "",
          "image": "",
          "rating": 4,
          "ratedBy": 45,
          "topReviews": [
            {
              "rating": 3,
              "name": "Johny Lobson",
              "thumbnail": "",
              "title": "Very good",
              "comment": "I used her services"
            },
            {
              "rating": 3,
              "name": "Johny Lobson",
              "thumbnail": "",
              "title": "Very good",
              "comment": "I used her services"
            }
          ],
          "description":
            "$ years of experience in kickboxing, Victoria is best suited to help you"
        },
        {
          "name": "Victoria",
          "id": "123",
          "image": "",
          "video": "",
          "rating": 4,
          "ratedBy": 45,
          "topReviews": [
            {
              "rating": 3,
              "name": "Johny Lobson",
              "thumbnail": "",
              "title": "Very good",
              "comment": "I used her services"
            },
            {
              "rating": 3,
              "name": "Johny Lobson",
              "thumbnail": "",
              "title": "Very good",
              "comment": "I used her services"
            }
          ],
          "description":
            "$ years of experience in kickboxing, Victoria is best suited to help you"
        },
        {
          "name": "Victoria",
          "id": "123",
          "video": "",
          "image": "",
          "rating": 4,
          "ratedBy": 45,
          "topReviews": [
            {
              "rating": 3,
              "name": "Johny Lobson",
              "thumbnail": "",
              "title": "Very good",
              "comment": "I used her services"
            },
            {
              "rating": 3,
              "name": "Johny Lobson",
              "thumbnail": "",
              "title": "Very good",
              "comment": "I used her services"
            }
          ],
          "description":
            "$ years of experience in kickboxing, Victoria is best suited to help you"
        },
        {
          "name": "Victoria",
          "id": "123",
          "video": "",
          "image": "",
          "rating": 4,
          "ratedBy": 45,
          "topReviews": [
            {
              "rating": 3,
              "name": "Johny Lobson",
              "thumbnail": "",
              "title": "Very good",
              "comment": "I used her services"
            },
            {
              "rating": 3,
              "name": "Johny Lobson",
              "thumbnail": "",
              "title": "Very good",
              "comment": "I used her services"
            }
          ],
          "description":
            "$ years of experience in kickboxing, Victoria is best suited to help you"
        },
        {
          "name": "Victoria",
          "id": "123",
          "image": "",
          "video": "",
          "rating": 4,
          "ratedBy": 45,
          "topReviews": [
            {
              "rating": 3,
              "name": "Johny Lobson",
              "thumbnail": "",
              "title": "Very good",
              "comment": "I used her services"
            },
            {
              "rating": 3,
              "name": "Johny Lobson",
              "thumbnail": "",
              "title": "Very good",
              "comment": "I used her services"
            }
          ],
          "description":
            "$ years of experience in kickboxing, Victoria is best suited to help you"
        }
      ]
    }
  ]
}
